{"openapi":"3.1.0","info":{"title":"Nissei 工数管理システム","description":"工数管理と請求処理のためのシステム","version":"1.0.0"},"paths":{"/":{"get":{"summary":"Health Check","operationId":"health_check__get","responses":{"200":{"description":"Successful Response","content":{"application/json":{"schema":{}}}}}}},"/api/auth/register":{"post":{"tags":["認証"],"summary":"Register User","description":"新規ユーザー登録","operationId":"register_user_api_auth_register_post","requestBody":{"content":{"application/json":{"schema":{"$ref":"#/components/schemas/UserCreate"}}},"required":true},"responses":{"201":{"description":"Successful Response","content":{"application/json":{"schema":{"$ref":"#/components/schemas/UserResponse"}}}},"422":{"description":"Validation Error","content":{"application/json":{"schema":{"$ref":"#/components/schemas/HTTPValidationError"}}}}}}},"/api/auth/login":{"post":{"tags":["認証"],"summary":"Login","description":"ログイン","operationId":"login_api_auth_login_post","requestBody":{"content":{"application/json":{"schema":{"$ref":"#/components/schemas/LoginRequest"}}},"required":true},"responses":{"200":{"description":"Successful Response","content":{"application/json":{"schema":{"$ref":"#/components/schemas/Token"}}}},"422":{"description":"Validation Error","content":{"application/json":{"schema":{"$ref":"#/components/schemas/HTTPValidationError"}}}}}}},"/api/auth/me":{"get":{"tags":["認証"],"summary":"Get Me","description":"現在のユーザー情報を取得","operationId":"get_me_api_auth_me_get","responses":{"200":{"description":"Successful Response","content":{"application/json":{"schema":{"$ref":"#/components/schemas/UserResponse"}}}}},"security":[{"HTTPBearer":[]}]}},"/api/projects":{"post":{"tags":["案件管理","projects"],"summary":"Create Project","description":"案件を新規作成","operationId":"create_project_api_projects_post","security":[{"HTTPBearer":[]}],"requestBody":{"required":true,"content":{"application/json":{"schema":{"$ref":"#/components/schemas/ProjectCreate"}}}},"responses":{"201":{"description":"Successful Response","content":{"application/json":{"schema":{"$ref":"#/components/schemas/ProjectResponse"}}}},"422":{"description":"Validation Error","content":{"application/json":{"schema":{"$ref":"#/components/schemas/HTTPValidationError"}}}}}},"get":{"tags":["案件管理","projects"],"summary":"List Projects","description":"案件一覧を取得","operationId":"list_projects_api_projects_get","security":[{"HTTPBearer":[]}],"parameters":[{"name":"page","in":"query","required":false,"schema":{"type":"integer","minimum":1,"description":"ページ番号","default":1,"title":"Page"},"description":"ページ番号"},{"name":"per_page","in":"query","required":false,"schema":{"type":"integer","maximum":100,"minimum":1,"description":"1ページあたりの件数","default":20,"title":"Per Page"},"description":"1ページあたりの件数"},{"name":"shinchoku_id","in":"query","required":false,"schema":{"anyOf":[{"type":"string","format":"uuid"},{"type":"null"}],"description":"進捗IDでフィルタ","title":"Shinchoku Id"},"description":"進捗IDでフィルタ"},{"name":"sagyou_kubun_id","in":"query","required":false,"schema":{"anyOf":[{"type":"string","format":"uuid"},{"type":"null"}],"description":"作業区分IDでフィルタ","title":"Sagyou Kubun Id"},"description":"作業区分IDでフィルタ"},{"name":"machine_no","in":"query","required":false,"schema":{"anyOf":[{"type":"string"},{"type":"null"}],"description":"機番で検索","title":"Machine No"},"description":"機番で検索"},{"name":"management_no","in":"query","required":false,"schema":{"anyOf":[{"type":"string"},{"type":"null"}],"description":"管理Noで検索","title":"Management No"},"description":"管理Noで検索"},{"name":"include_inactive","in":"query","required":false,"schema":{"type":"boolean","description":"無効な案件も含める","default":false,"title":"Include Inactive"},"description":"無効な案件も含める"}],"responses":{"200":{"description":"Successful Response","content":{"application/json":{"schema":{"$ref":"#/components/schemas/ProjectListResponse"}}}},"422":{"description":"Validation Error","content":{"application/json":{"schema":{"$ref":"#/components/schemas/HTTPValidationError"}}}}}}},"/api/projects/{project_id}":{"get":{"tags":["案件管理","projects"],"summary":"Get Project","description":"案件詳細を取得","operationId":"get_project_api_projects__project_id__get","security":[{"HTTPBearer":[]}],"parameters":[{"name":"project_id","in":"path","required":true,"schema":{"type":"string","format":"uuid","title":"Project Id"}}],"responses":{"200":{"description":"Successful Response","content":{"application/json":{"schema":{"$ref":"#/components/schemas/ProjectResponse"}}}},"422":{"description":"Validation Error","content":{"application/json":{"schema":{"$ref":"#/components/schemas/HTTPValidationError"}}}}}},"put":{"tags":["案件管理","projects"],"summary":"Update Project","description":"案件を更新","operationId":"update_project_api_projects__project_id__put","security":[{"HTTPBearer":[]}],"parameters":[{"name":"project_id","in":"path","required":true,"schema":{"type":"string","format":"uuid","title":"Project Id"}}],"requestBody":{"required":true,"content":{"application/json":{"schema":{"$ref":"#/components/schemas/ProjectUpdate"}}}},"responses":{"200":{"description":"Successful Response","content":{"application/json":{"schema":{"$ref":"#/components/schemas/ProjectResponse"}}}},"422":{"description":"Validation Error","content":{"application/json":{"schema":{"$ref":"#/components/schemas/HTTPValidationError"}}}}}},"delete":{"tags":["案件管理","projects"],"summary":"Delete Project","description":"案件を論理削除","operationId":"delete_project_api_projects__project_id__delete","security":[{"HTTPBearer":[]}],"parameters":[{"name":"project_id","in":"path","required":true,"schema":{"type":"string","format":"uuid","title":"Project Id"}}],"responses":{"204":{"description":"Successful Response"},"422":{"description":"Validation Error","content":{"application/json":{"schema":{"$ref":"#/components/schemas/HTTPValidationError"}}}}}}},"/api/worklogs":{"post":{"tags":["工数入力"],"summary":"Create Worklog","description":"工数入力を新規作成","operationId":"create_worklog_api_worklogs_post","security":[{"HTTPBearer":[]}],"requestBody":{"required":true,"content":{"application/json":{"schema":{"$ref":"#/components/schemas/WorkLogCreate"}}}},"responses":{"201":{"description":"Successful Response","content":{"application/json":{"schema":{"$ref":"#/components/schemas/WorkLogResponse"}}}},"422":{"description":"Validation Error","content":{"application/json":{"schema":{"$ref":"#/components/schemas/HTTPValidationError"}}}}}},"get":{"tags":["工数入力"],"summary":"List Worklogs","description":"工数入力一覧を取得","operationId":"list_worklogs_api_worklogs_get","security":[{"HTTPBearer":[]}],"parameters":[{"name":"page","in":"query","required":false,"schema":{"type":"integer","minimum":1,"description":"ページ番号","default":1,"title":"Page"},"description":"ページ番号"},{"name":"per_page","in":"query","required":false,"schema":{"type":"integer","maximum":100,"minimum":1,"description":"1ページあたりの件数","default":20,"title":"Per Page"},"description":"1ページあたりの件数"},{"name":"project_id","in":"query","required":false,"schema":{"anyOf":[{"type":"string","format":"uuid"},{"type":"null"}],"description":"案件IDでフィルタ","title":"Project Id"},"description":"案件IDでフィルタ"},{"name":"work_date","in":"query","required":false,"schema":{"anyOf":[{"type":"string","format":"date"},{"type":"null"}],"description":"作業日でフィルタ","title":"Work Date"},"description":"作業日でフィルタ"},{"name":"user_id","in":"query","required":false,"schema":{"anyOf":[{"type":"string","format":"uuid"},{"type":"null"}],"description":"ユーザーIDでフィルタ","title":"User Id"},"description":"ユーザーIDでフィルタ"}],"responses":{"200":{"description":"Successful Response","content":{"application/json":{"schema":{"$ref":"#/components/schemas/WorkLogListResponse"}}}},"422":{"description":"Validation Error","content":{"application/json":{"schema":{"$ref":"#/components/schemas/HTTPValidationError"}}}}}}},"/api/worklogs/{worklog_id}":{"get":{"tags":["工数入力"],"summary":"Get Worklog","description":"工数入力詳細を取得","operationId":"get_worklog_api_worklogs__worklog_id__get","security":[{"HTTPBearer":[]}],"parameters":[{"name":"worklog_id","in":"path","required":true,"schema":{"type":"string","format":"uuid","title":"Worklog Id"}}],"responses":{"200":{"description":"Successful Response","content":{"application/json":{"schema":{"$ref":"#/components/schemas/WorkLogResponse"}}}},"422":{"description":"Validation Error","content":{"application/json":{"schema":{"$ref":"#/components/schemas/HTTPValidationError"}}}}}},"put":{"tags":["工数入力"],"summary":"Update Worklog","description":"工数入力を更新","operationId":"update_worklog_api_worklogs__worklog_id__put","security":[{"HTTPBearer":[]}],"parameters":[{"name":"worklog_id","in":"path","required":true,"schema":{"type":"string","format":"uuid","title":"Worklog Id"}}],"requestBody":{"required":true,"content":{"application/json":{"schema":{"$ref":"#/components/schemas/WorkLogUpdate"}}}},"responses":{"200":{"description":"Successful Response","content":{"application/json":{"schema":{"$ref":"#/components/schemas/WorkLogResponse"}}}},"422":{"description":"Validation Error","content":{"application/json":{"schema":{"$ref":"#/components/schemas/HTTPValidationError"}}}}}},"delete":{"tags":["工数入力"],"summary":"Delete Worklog","description":"工数入力を削除","operationId":"delete_worklog_api_worklogs__worklog_id__delete","security":[{"HTTPBearer":[]}],"parameters":[{"name":"worklog_id","in":"path","required":true,"schema":{"type":"string","format":"uuid","title":"Worklog Id"}}],"responses":{"204":{"description":"Successful Response"},"422":{"description":"Validation Error","content":{"application/json":{"schema":{"$ref":"#/components/schemas/HTTPValidationError"}}}}}}},"/api/worklogs/summary/{project_id}":{"get":{"tags":["工数入力"],"summary":"Get Worklog Summary","description":"案件の工数集計を取得","operationId":"get_worklog_summary_api_worklogs_summary__project_id__get","security":[{"HTTPBearer":[]}],"parameters":[{"name":"project_id","in":"path","required":true,"schema":{"type":"string","format":"uuid","title":"Project Id"}}],"responses":{"200":{"description":"Successful Response","content":{"application/json":{"schema":{}}}},"422":{"description":"Validation Error","content":{"application/json":{"schema":{"$ref":"#/components/schemas/HTTPValidationError"}}}}}}},"/api/invoices/preview":{"get":{"tags":["請求"],"summary":"Preview Invoice","description":"指定月の請求書プレビュー（worklogsから実工数を集計）","operationId":"preview_invoice_api_invoices_preview_get","security":[{"HTTPBearer":[]}],"parameters":[{"name":"month","in":"query","required":true,"schema":{"type":"string","description":"YYYY-MM形式の月","title":"Month"},"description":"YYYY-MM形式の月"}],"responses":{"200":{"description":"Successful Response","content":{"application/json":{"schema":{"$ref":"#/components/schemas/InvoicePreviewResponse"}}}},"422":{"description":"Validation Error","content":{"application/json":{"schema":{"$ref":"#/components/schemas/HTTPValidationError"}}}}}}},"/api/invoices/close":{"post":{"tags":["請求"],"summary":"Close Invoice","description":"請求書を確定（管理者のみ）","operationId":"close_invoice_api_invoices_close_post","security":[{"HTTPBearer":[]}],"parameters":[{"name":"month","in":"query","required":true,"schema":{"type":"string","description":"YYYY-MM形式の月","title":"Month"},"description":"YYYY-MM形式の月"}],"responses":{"200":{"description":"Successful Response","content":{"application/json":{"schema":{"$ref":"#/components/schemas/InvoiceResponse"}}}},"422":{"description":"Validation Error","content":{"application/json":{"schema":{"$ref":"#/components/schemas/HTTPValidationError"}}}}}}},"/api/invoices/export":{"get":{"tags":["請求"],"summary":"Export Invoice Csv","description":"請求書CSVエクスポート","operationId":"export_invoice_csv_api_invoices_export_get","security":[{"HTTPBearer":[]}],"parameters":[{"name":"month","in":"query","required":true,"schema":{"type":"string","description":"YYYY-MM形式の月","title":"Month"},"description":"YYYY-MM形式の月"}],"responses":{"200":{"description":"Successful Response","content":{"application/json":{"schema":{}}}},"422":{"description":"Validation Error","content":{"application/json":{"schema":{"$ref":"#/components/schemas/HTTPValidationError"}}}}}}},"/api/invoices/{invoice_id}":{"get":{"tags":["請求"],"summary":"Get Invoice","description":"請求書詳細を取得","operationId":"get_invoice_api_invoices__invoice_id__get","security":[{"HTTPBearer":[]}],"parameters":[{"name":"invoice_id","in":"path","required":true,"schema":{"type":"string","format":"uuid","title":"Invoice Id"}}],"responses":{"200":{"description":"Successful Response","content":{"application/json":{"schema":{"$ref":"#/components/schemas/InvoiceResponse"}}}},"422":{"description":"Validation Error","content":{"application/json":{"schema":{"$ref":"#/components/schemas/HTTPValidationError"}}}}}},"patch":{"tags":["請求"],"summary":"Update Invoice","description":"請求書を更新（管理者のみ、ステータス変更のみ）","operationId":"update_invoice_api_invoices__invoice_id__patch","security":[{"HTTPBearer":[]}],"parameters":[{"name":"invoice_id","in":"path","required":true,"schema":{"type":"string","format":"uuid","title":"Invoice Id"}}],"requestBody":{"required":true,"content":{"application/json":{"schema":{"$ref":"#/components/schemas/InvoiceUpdate"}}}},"responses":{"200":{"description":"Successful Response","content":{"application/json":{"schema":{"$ref":"#/components/schemas/InvoiceResponse"}}}},"422":{"description":"Validation Error","content":{"application/json":{"schema":{"$ref":"#/components/schemas/HTTPValidationError"}}}}}},"delete":{"tags":["請求"],"summary":"Delete Invoice","description":"請求書を削除（管理者のみ、CASCADE）","operationId":"delete_invoice_api_invoices__invoice_id__delete","security":[{"HTTPBearer":[]}],"parameters":[{"name":"invoice_id","in":"path","required":true,"schema":{"type":"string","format":"uuid","title":"Invoice Id"}}],"responses":{"200":{"description":"Successful Response","content":{"application/json":{"schema":{}}}},"422":{"description":"Validation Error","content":{"application/json":{"schema":{"$ref":"#/components/schemas/HTTPValidationError"}}}}}}},"/api/invoices":{"get":{"tags":["請求"],"summary":"List Invoices","description":"請求書一覧を取得","operationId":"list_invoices_api_invoices_get","security":[{"HTTPBearer":[]}],"parameters":[{"name":"status","in":"query","required":false,"schema":{"anyOf":[{"type":"string"},{"type":"null"}],"description":"ステータスフィルタ","title":"Status"},"description":"ステータスフィルタ"}],"responses":{"200":{"description":"Successful Response","content":{"application/json":{"schema":{"type":"array","items":{"$ref":"#/components/schemas/InvoiceResponse"},"title":"Response List Invoices Api Invoices Get"}}}},"422":{"description":"Validation Error","content":{"application/json":{"schema":{"$ref":"#/components/schemas/HTTPValidationError"}}}}}}},"/api/materials/upload":{"post":{"tags":["資料"],"summary":"Upload Material","description":"資料アップロード","operationId":"upload_material_api_materials_upload_post","security":[{"HTTPBearer":[]}],"parameters":[{"name":"title","in":"query","required":true,"schema":{"type":"string","description":"資料タイトル","title":"Title"},"description":"資料タイトル"},{"name":"scope","in":"query","required":true,"schema":{"type":"string","description":"スコープレベル: machine, model, tonnage, series","title":"Scope"},"description":"スコープレベル: machine, model, tonnage, series"},{"name":"series","in":"query","required":true,"schema":{"type":"string","description":"シリーズ名（NEX, HMX等）","title":"Series"},"description":"シリーズ名（NEX, HMX等）"},{"name":"machine_no","in":"query","required":false,"schema":{"anyOf":[{"type":"string"},{"type":"null"}],"description":"特定機番（scope=machineの場合）","title":"Machine No"},"description":"特定機番（scope=machineの場合）"},{"name":"model","in":"query","required":false,"schema":{"anyOf":[{"type":"string"},{"type":"null"}],"description":"特定機種（scope=modelの場合）","title":"Model"},"description":"特定機種（scope=modelの場合）"},{"name":"tonnage","in":"query","required":false,"schema":{"anyOf":[{"type":"integer"},{"type":"null"}],"description":"トン数（scope=tonnageの場合）","title":"Tonnage"},"description":"トン数（scope=tonnageの場合）"}],"requestBody":{"required":true,"content":{"multipart/form-data":{"schema":{"$ref":"#/components/schemas/Body_upload_material_api_materials_upload_post"}}}},"responses":{"200":{"description":"Successful Response","content":{"application/json":{"schema":{"$ref":"#/components/schemas/MaterialResponse"}}}},"422":{"description":"Validation Error","content":{"application/json":{"schema":{"$ref":"#/components/schemas/HTTPValidationError"}}}}}}},"/api/materials/search":{"get":{"tags":["資料"],"summary":"Search Materials","description":"資料検索（階層的スコープ検索）\n\n優先度: machine > model > tonnage > series\n例: machine_no指定時は、そのmachine専用 + model共通 + tonnage共通 + series共通を全て返す","operationId":"search_materials_api_materials_search_get","security":[{"HTTPBearer":[]}],"parameters":[{"name":"machine_no","in":"query","required":false,"schema":{"anyOf":[{"type":"string"},{"type":"null"}],"description":"機番で検索","title":"Machine No"},"description":"機番で検索"},{"name":"model","in":"query","required":false,"schema":{"anyOf":[{"type":"string"},{"type":"null"}],"description":"機種で検索","title":"Model"},"description":"機種で検索"},{"name":"series","in":"query","required":false,"schema":{"anyOf":[{"type":"string"},{"type":"null"}],"description":"シリーズで検索","title":"Series"},"description":"シリーズで検索"},{"name":"tonnage","in":"query","required":false,"schema":{"anyOf":[{"type":"integer"},{"type":"null"}],"description":"トン数で検索","title":"Tonnage"},"description":"トン数で検索"},{"name":"scope","in":"query","required":false,"schema":{"anyOf":[{"type":"string"},{"type":"null"}],"description":"スコープで絞り込み","title":"Scope"},"description":"スコープで絞り込み"}],"responses":{"200":{"description":"Successful Response","content":{"application/json":{"schema":{"type":"array","items":{"$ref":"#/components/schemas/MaterialResponse"},"title":"Response Search Materials Api Materials Search Get"}}}},"422":{"description":"Validation Error","content":{"application/json":{"schema":{"$ref":"#/components/schemas/HTTPValidationError"}}}}}}},"/api/materials/{material_id}":{"get":{"tags":["資料"],"summary":"Get Material","description":"資料詳細を取得","operationId":"get_material_api_materials__material_id__get","security":[{"HTTPBearer":[]}],"parameters":[{"name":"material_id","in":"path","required":true,"schema":{"type":"string","format":"uuid","title":"Material Id"}}],"responses":{"200":{"description":"Successful Response","content":{"application/json":{"schema":{"$ref":"#/components/schemas/MaterialResponse"}}}},"422":{"description":"Validation Error","content":{"application/json":{"schema":{"$ref":"#/components/schemas/HTTPValidationError"}}}}}},"delete":{"tags":["資料"],"summary":"Delete Material","description":"資料を削除","operationId":"delete_material_api_materials__material_id__delete","security":[{"HTTPBearer":[]}],"parameters":[{"name":"material_id","in":"path","required":true,"schema":{"type":"string","format":"uuid","title":"Material Id"}}],"responses":{"200":{"description":"Successful Response","content":{"application/json":{"schema":{}}}},"422":{"description":"Validation Error","content":{"application/json":{"schema":{"$ref":"#/components/schemas/HTTPValidationError"}}}}}}},"/api/chuiten/master":{"get":{"tags":["注意点"],"summary":"List Chuiten Master","description":"注意点マスタ一覧を取得","operationId":"list_chuiten_master_api_chuiten_master_get","security":[{"HTTPBearer":[]}],"parameters":[{"name":"category_id","in":"query","required":false,"schema":{"anyOf":[{"type":"string","format":"uuid"},{"type":"null"}],"description":"カテゴリIDで絞り込み","title":"Category Id"},"description":"カテゴリIDで絞り込み"},{"name":"target_series","in":"query","required":false,"schema":{"anyOf":[{"type":"string"},{"type":"null"}],"description":"対象シリーズで絞り込み","title":"Target Series"},"description":"対象シリーズで絞り込み"}],"responses":{"200":{"description":"Successful Response","content":{"application/json":{"schema":{"type":"array","items":{"type":"object"},"title":"Response List Chuiten Master Api Chuiten Master Get"}}}},"422":{"description":"Validation Error","content":{"application/json":{"schema":{"$ref":"#/components/schemas/HTTPValidationError"}}}}}},"post":{"tags":["注意点"],"summary":"Create Chuiten Master","description":"注意点マスタを追加","operationId":"create_chuiten_master_api_chuiten_master_post","security":[{"HTTPBearer":[]}],"parameters":[{"name":"category_id","in":"query","required":true,"schema":{"type":"string","format":"uuid","description":"カテゴリID","title":"Category Id"},"description":"カテゴリID"},{"name":"content","in":"query","required":true,"schema":{"type":"string","description":"注意点内容","title":"Content"},"description":"注意点内容"},{"name":"target_series","in":"query","required":false,"schema":{"anyOf":[{"type":"string"},{"type":"null"}],"description":"対象シリーズ","title":"Target Series"},"description":"対象シリーズ"},{"name":"target_board","in":"query","required":false,"schema":{"anyOf":[{"type":"string"},{"type":"null"}],"description":"対象盤","title":"Target Board"},"description":"対象盤"},{"name":"author","in":"query","required":false,"schema":{"anyOf":[{"type":"string"},{"type":"null"}],"description":"作成者名","title":"Author"},"description":"作成者名"},{"name":"notes","in":"query","required":false,"schema":{"anyOf":[{"type":"string"},{"type":"null"}],"description":"備考","title":"Notes"},"description":"備考"}],"responses":{"200":{"description":"Successful Response","content":{"application/json":{"schema":{"type":"object","title":"Response Create Chuiten Master Api Chuiten Master Post"}}}},"422":{"description":"Validation Error","content":{"application/json":{"schema":{"$ref":"#/components/schemas/HTTPValidationError"}}}}}}},"/api/chuiten/master/{master_id}":{"put":{"tags":["注意点"],"summary":"Update Chuiten Master","description":"注意点マスタを更新","operationId":"update_chuiten_master_api_chuiten_master__master_id__put","security":[{"HTTPBearer":[]}],"parameters":[{"name":"master_id","in":"path","required":true,"schema":{"type":"string","format":"uuid","title":"Master Id"}},{"name":"category_id","in":"query","required":false,"schema":{"anyOf":[{"type":"string","format":"uuid"},{"type":"null"}],"title":"Category Id"}},{"name":"content","in":"query","required":false,"schema":{"anyOf":[{"type":"string"},{"type":"null"}],"title":"Content"}},{"name":"target_series","in":"query","required":false,"schema":{"anyOf":[{"type":"string"},{"type":"null"}],"title":"Target Series"}},{"name":"target_board","in":"query","required":false,"schema":{"anyOf":[{"type":"string"},{"type":"null"}],"title":"Target Board"}},{"name":"author","in":"query","required":false,"schema":{"anyOf":[{"type":"string"},{"type":"null"}],"title":"Author"}},{"name":"notes","in":"query","required":false,"schema":{"anyOf":[{"type":"string"},{"type":"null"}],"title":"Notes"}}],"responses":{"200":{"description":"Successful Response","content":{"application/json":{"schema":{"type":"object","title":"Response Update Chuiten Master Api Chuiten Master  Master Id  Put"}}}},"422":{"description":"Validation Error","content":{"application/json":{"schema":{"$ref":"#/components/schemas/HTTPValidationError"}}}}}},"delete":{"tags":["注意点"],"summary":"Delete Chuiten Master","description":"注意点マスタを削除","operationId":"delete_chuiten_master_api_chuiten_master__master_id__delete","security":[{"HTTPBearer":[]}],"parameters":[{"name":"master_id","in":"path","required":true,"schema":{"type":"string","format":"uuid","title":"Master Id"}}],"responses":{"200":{"description":"Successful Response","content":{"application/json":{"schema":{}}}},"422":{"description":"Validation Error","content":{"application/json":{"schema":{"$ref":"#/components/schemas/HTTPValidationError"}}}}}}},"/api/chuiten/categories":{"get":{"tags":["注意点"],"summary":"List Chuiten Categories","description":"注意点カテゴリ一覧を取得","operationId":"list_chuiten_categories_api_chuiten_categories_get","security":[{"HTTPBearer":[]}],"responses":{"200":{"description":"Successful Response","content":{"application/json":{"schema":{"type":"array","items":{"type":"object"},"title":"Response List Chuiten Categories Api Chuiten Categories Get"}}}}}},"post":{"tags":["注意点"],"summary":"Create Chuiten Category","description":"注意点カテゴリを追加","operationId":"create_chuiten_category_api_chuiten_categories_post","security":[{"HTTPBearer":[]}],"parameters":[{"name":"name","in":"query","required":true,"schema":{"type":"string","description":"カテゴリ名","title":"Name"},"description":"カテゴリ名"},{"name":"sort_order","in":"query","required":false,"schema":{"type":"integer","description":"並び順","default":0,"title":"Sort Order"},"description":"並び順"}],"responses":{"200":{"description":"Successful Response","content":{"application/json":{"schema":{"type":"object","title":"Response Create Chuiten Category Api Chuiten Categories Post"}}}},"422":{"description":"Validation Error","content":{"application/json":{"schema":{"$ref":"#/components/schemas/HTTPValidationError"}}}}}}},"/api/masters/shinchoku":{"get":{"tags":["マスタ","masters"],"summary":"List Shinchoku","description":"進捗マスタ一覧取得","operationId":"list_shinchoku_api_masters_shinchoku_get","security":[{"HTTPBearer":[]}],"parameters":[{"name":"skip","in":"query","required":false,"schema":{"type":"integer","default":0,"title":"Skip"}},{"name":"limit","in":"query","required":false,"schema":{"type":"integer","default":100,"title":"Limit"}},{"name":"include_inactive","in":"query","required":false,"schema":{"type":"boolean","default":false,"title":"Include Inactive"}}],"responses":{"200":{"description":"Successful Response","content":{"application/json":{"schema":{"type":"array","items":{"$ref":"#/components/schemas/MasterShinchokuResponse"},"title":"Response List Shinchoku Api Masters Shinchoku Get"}}}},"422":{"description":"Validation Error","content":{"application/json":{"schema":{"$ref":"#/components/schemas/HTTPValidationError"}}}}}},"post":{"tags":["マスタ","masters"],"summary":"Create Shinchoku","description":"進捗マスタ作成","operationId":"create_shinchoku_api_masters_shinchoku_post","security":[{"HTTPBearer":[]}],"requestBody":{"required":true,"content":{"application/json":{"schema":{"$ref":"#/components/schemas/MasterShinchokuCreate"}}}},"responses":{"201":{"description":"Successful Response","content":{"application/json":{"schema":{"$ref":"#/components/schemas/MasterShinchokuResponse"}}}},"422":{"description":"Validation Error","content":{"application/json":{"schema":{"$ref":"#/components/schemas/HTTPValidationError"}}}}}}},"/api/masters/shinchoku/{item_id}":{"get":{"tags":["マスタ","masters"],"summary":"Get Shinchoku","description":"進捗マスタ詳細取得","operationId":"get_shinchoku_api_masters_shinchoku__item_id__get","security":[{"HTTPBearer":[]}],"parameters":[{"name":"item_id","in":"path","required":true,"schema":{"type":"string","format":"uuid","title":"Item Id"}}],"responses":{"200":{"description":"Successful Response","content":{"application/json":{"schema":{"$ref":"#/components/schemas/MasterShinchokuResponse"}}}},"422":{"description":"Validation Error","content":{"application/json":{"schema":{"$ref":"#/components/schemas/HTTPValidationError"}}}}}},"put":{"tags":["マスタ","masters"],"summary":"Update Shinchoku","description":"進捗マスタ更新","operationId":"update_shinchoku_api_masters_shinchoku__item_id__put","security":[{"HTTPBearer":[]}],"parameters":[{"name":"item_id","in":"path","required":true,"schema":{"type":"string","format":"uuid","title":"Item Id"}}],"requestBody":{"required":true,"content":{"application/json":{"schema":{"$ref":"#/components/schemas/MasterShinchokuUpdate"}}}},"responses":{"200":{"description":"Successful Response","content":{"application/json":{"schema":{"$ref":"#/components/schemas/MasterShinchokuResponse"}}}},"422":{"description":"Validation Error","content":{"application/json":{"schema":{"$ref":"#/components/schemas/HTTPValidationError"}}}}}},"delete":{"tags":["マスタ","masters"],"summary":"Delete Shinchoku","description":"進捗マスタ論理削除","operationId":"delete_shinchoku_api_masters_shinchoku__item_id__delete","security":[{"HTTPBearer":[]}],"parameters":[{"name":"item_id","in":"path","required":true,"schema":{"type":"string","format":"uuid","title":"Item Id"}}],"responses":{"204":{"description":"Successful Response"},"422":{"description":"Validation Error","content":{"application/json":{"schema":{"$ref":"#/components/schemas/HTTPValidationError"}}}}}}},"/api/masters/sagyou-kubun":{"get":{"tags":["マスタ","masters"],"summary":"List Sagyou Kubun","description":"作業区分マスタ一覧取得","operationId":"list_sagyou_kubun_api_masters_sagyou_kubun_get","security":[{"HTTPBearer":[]}],"parameters":[{"name":"skip","in":"query","required":false,"schema":{"type":"integer","default":0,"title":"Skip"}},{"name":"limit","in":"query","required":false,"schema":{"type":"integer","default":100,"title":"Limit"}},{"name":"include_inactive","in":"query","required":false,"schema":{"type":"boolean","default":false,"title":"Include Inactive"}}],"responses":{"200":{"description":"Successful Response","content":{"application/json":{"schema":{"type":"array","items":{"$ref":"#/components/schemas/MasterSagyouKubunResponse"},"title":"Response List Sagyou Kubun Api Masters Sagyou Kubun Get"}}}},"422":{"description":"Validation Error","content":{"application/json":{"schema":{"$ref":"#/components/schemas/HTTPValidationError"}}}}}},"post":{"tags":["マスタ","masters"],"summary":"Create Sagyou Kubun","description":"作業区分マスタ作成","operationId":"create_sagyou_kubun_api_masters_sagyou_kubun_post","security":[{"HTTPBearer":[]}],"requestBody":{"required":true,"content":{"application/json":{"schema":{"$ref":"#/components/schemas/MasterSagyouKubunCreate"}}}},"responses":{"201":{"description":"Successful Response","content":{"application/json":{"schema":{"$ref":"#/components/schemas/MasterSagyouKubunResponse"}}}},"422":{"description":"Validation Error","content":{"application/json":{"schema":{"$ref":"#/components/schemas/HTTPValidationError"}}}}}}},"/api/masters/sagyou-kubun/{item_id}":{"get":{"tags":["マスタ","masters"],"summary":"Get Sagyou Kubun","description":"作業区分マスタ詳細取得","operationId":"get_sagyou_kubun_api_masters_sagyou_kubun__item_id__get","security":[{"HTTPBearer":[]}],"parameters":[{"name":"item_id","in":"path","required":true,"schema":{"type":"string","format":"uuid","title":"Item Id"}}],"responses":{"200":{"description":"Successful Response","content":{"application/json":{"schema":{"$ref":"#/components/schemas/MasterSagyouKubunResponse"}}}},"422":{"description":"Validation Error","content":{"application/json":{"schema":{"$ref":"#/components/schemas/HTTPValidationError"}}}}}},"put":{"tags":["マスタ","masters"],"summary":"Update Sagyou Kubun","description":"作業区分マスタ更新","operationId":"update_sagyou_kubun_api_masters_sagyou_kubun__item_id__put","security":[{"HTTPBearer":[]}],"parameters":[{"name":"item_id","in":"path","required":true,"schema":{"type":"string","format":"uuid","title":"Item Id"}}],"requestBody":{"required":true,"content":{"application/json":{"schema":{"$ref":"#/components/schemas/MasterSagyouKubunUpdate"}}}},"responses":{"200":{"description":"Successful Response","content":{"application/json":{"schema":{"$ref":"#/components/schemas/MasterSagyouKubunResponse"}}}},"422":{"description":"Validation Error","content":{"application/json":{"schema":{"$ref":"#/components/schemas/HTTPValidationError"}}}}}},"delete":{"tags":["マスタ","masters"],"summary":"Delete Sagyou Kubun","description":"作業区分マスタ論理削除","operationId":"delete_sagyou_kubun_api_masters_sagyou_kubun__item_id__delete","security":[{"HTTPBearer":[]}],"parameters":[{"name":"item_id","in":"path","required":true,"schema":{"type":"string","format":"uuid","title":"Item Id"}}],"responses":{"204":{"description":"Successful Response"},"422":{"description":"Validation Error","content":{"application/json":{"schema":{"$ref":"#/components/schemas/HTTPValidationError"}}}}}}},"/api/masters/toiawase":{"get":{"tags":["マスタ","masters"],"summary":"List Toiawase","description":"問い合わせマスタ一覧取得","operationId":"list_toiawase_api_masters_toiawase_get","security":[{"HTTPBearer":[]}],"parameters":[{"name":"skip","in":"query","required":false,"schema":{"type":"integer","default":0,"title":"Skip"}},{"name":"limit","in":"query","required":false,"schema":{"type":"integer","default":100,"title":"Limit"}},{"name":"include_inactive","in":"query","required":false,"schema":{"type":"boolean","default":false,"title":"Include Inactive"}}],"responses":{"200":{"description":"Successful Response","content":{"application/json":{"schema":{"type":"array","items":{"$ref":"#/components/schemas/MasterToiawaseResponse"},"title":"Response List Toiawase Api Masters Toiawase Get"}}}},"422":{"description":"Validation Error","content":{"application/json":{"schema":{"$ref":"#/components/schemas/HTTPValidationError"}}}}}},"post":{"tags":["マスタ","masters"],"summary":"Create Toiawase","description":"問い合わせマスタ作成","operationId":"create_toiawase_api_masters_toiawase_post","security":[{"HTTPBearer":[]}],"requestBody":{"required":true,"content":{"application/json":{"schema":{"$ref":"#/components/schemas/MasterToiawaseCreate"}}}},"responses":{"201":{"description":"Successful Response","content":{"application/json":{"schema":{"$ref":"#/components/schemas/MasterToiawaseResponse"}}}},"422":{"description":"Validation Error","content":{"application/json":{"schema":{"$ref":"#/components/schemas/HTTPValidationError"}}}}}}},"/api/masters/toiawase/{item_id}":{"get":{"tags":["マスタ","masters"],"summary":"Get Toiawase","description":"問い合わせマスタ詳細取得","operationId":"get_toiawase_api_masters_toiawase__item_id__get","security":[{"HTTPBearer":[]}],"parameters":[{"name":"item_id","in":"path","required":true,"schema":{"type":"string","format":"uuid","title":"Item Id"}}],"responses":{"200":{"description":"Successful Response","content":{"application/json":{"schema":{"$ref":"#/components/schemas/MasterToiawaseResponse"}}}},"422":{"description":"Validation Error","content":{"application/json":{"schema":{"$ref":"#/components/schemas/HTTPValidationError"}}}}}},"put":{"tags":["マスタ","masters"],"summary":"Update Toiawase","description":"問い合わせマスタ更新","operationId":"update_toiawase_api_masters_toiawase__item_id__put","security":[{"HTTPBearer":[]}],"parameters":[{"name":"item_id","in":"path","required":true,"schema":{"type":"string","format":"uuid","title":"Item Id"}}],"requestBody":{"required":true,"content":{"application/json":{"schema":{"$ref":"#/components/schemas/MasterToiawaseUpdate"}}}},"responses":{"200":{"description":"Successful Response","content":{"application/json":{"schema":{"$ref":"#/components/schemas/MasterToiawaseResponse"}}}},"422":{"description":"Validation Error","content":{"application/json":{"schema":{"$ref":"#/components/schemas/HTTPValidationError"}}}}}},"delete":{"tags":["マスタ","masters"],"summary":"Delete Toiawase","description":"問い合わせマスタ論理削除","operationId":"delete_toiawase_api_masters_toiawase__item_id__delete","security":[{"HTTPBearer":[]}],"parameters":[{"name":"item_id","in":"path","required":true,"schema":{"type":"string","format":"uuid","title":"Item Id"}}],"responses":{"204":{"description":"Successful Response"},"422":{"description":"Validation Error","content":{"application/json":{"schema":{"$ref":"#/components/schemas/HTTPValidationError"}}}}}}},"/api/masters/machine-series":{"get":{"tags":["マスタ","masters"],"summary":"List Machine Series","description":"機種シリーズマスタ一覧取得","operationId":"list_machine_series_api_masters_machine_series_get","security":[{"HTTPBearer":[]}],"parameters":[{"name":"skip","in":"query","required":false,"schema":{"type":"integer","default":0,"title":"Skip"}},{"name":"limit","in":"query","required":false,"schema":{"type":"integer","default":100,"title":"Limit"}},{"name":"include_inactive","in":"query","required":false,"schema":{"type":"boolean","default":false,"title":"Include Inactive"}}],"responses":{"200":{"description":"Successful Response","content":{"application/json":{"schema":{"type":"array","items":{"$ref":"#/components/schemas/MachineSeriesMasterResponse"},"title":"Response List Machine Series Api Masters Machine Series Get"}}}},"422":{"description":"Validation Error","content":{"application/json":{"schema":{"$ref":"#/components/schemas/HTTPValidationError"}}}}}},"post":{"tags":["マスタ","masters"],"summary":"Create Machine Series","description":"機種シリーズマスタ作成","operationId":"create_machine_series_api_masters_machine_series_post","security":[{"HTTPBearer":[]}],"requestBody":{"required":true,"content":{"application/json":{"schema":{"$ref":"#/components/schemas/MachineSeriesMasterCreate"}}}},"responses":{"201":{"description":"Successful Response","content":{"application/json":{"schema":{"$ref":"#/components/schemas/MachineSeriesMasterResponse"}}}},"422":{"description":"Validation Error","content":{"application/json":{"schema":{"$ref":"#/components/schemas/HTTPValidationError"}}}}}}},"/api/masters/machine-series/{item_id}":{"get":{"tags":["マスタ","masters"],"summary":"Get Machine Series","description":"機種シリーズマスタ詳細取得","operationId":"get_machine_series_api_masters_machine_series__item_id__get","security":[{"HTTPBearer":[]}],"parameters":[{"name":"item_id","in":"path","required":true,"schema":{"type":"string","format":"uuid","title":"Item Id"}}],"responses":{"200":{"description":"Successful Response","content":{"application/json":{"schema":{"$ref":"#/components/schemas/MachineSeriesMasterResponse"}}}},"422":{"description":"Validation Error","content":{"application/json":{"schema":{"$ref":"#/components/schemas/HTTPValidationError"}}}}}},"put":{"tags":["マスタ","masters"],"summary":"Update Machine Series","description":"機種シリーズマスタ更新","operationId":"update_machine_series_api_masters_machine_series__item_id__put","security":[{"HTTPBearer":[]}],"parameters":[{"name":"item_id","in":"path","required":true,"schema":{"type":"string","format":"uuid","title":"Item Id"}}],"requestBody":{"required":true,"content":{"application/json":{"schema":{"$ref":"#/components/schemas/MachineSeriesMasterUpdate"}}}},"responses":{"200":{"description":"Successful Response","content":{"application/json":{"schema":{"$ref":"#/components/schemas/MachineSeriesMasterResponse"}}}},"422":{"description":"Validation Error","content":{"application/json":{"schema":{"$ref":"#/components/schemas/HTTPValidationError"}}}}}},"delete":{"tags":["マスタ","masters"],"summary":"Delete Machine Series","description":"機種シリーズマスタ論理削除","operationId":"delete_machine_series_api_masters_machine_series__item_id__delete","security":[{"HTTPBearer":[]}],"parameters":[{"name":"item_id","in":"path","required":true,"schema":{"type":"string","format":"uuid","title":"Item Id"}}],"responses":{"204":{"description":"Successful Response"},"422":{"description":"Validation Error","content":{"application/json":{"schema":{"$ref":"#/components/schemas/HTTPValidationError"}}}}}}},"/api/admin/users":{"get":{"tags":["管理者"],"summary":"List Users","description":"全ユーザー一覧取得（管理者のみ）","operationId":"list_users_api_admin_users_get","responses":{"200":{"description":"Successful Response","content":{"application/json":{"schema":{}}}}},"security":[{"HTTPBearer":[]}]}},"/api/admin/users/{user_id}":{"delete":{"tags":["管理者"],"summary":"Delete User","description":"ユーザー削除（管理者のみ）","operationId":"delete_user_api_admin_users__user_id__delete","security":[{"HTTPBearer":[]}],"parameters":[{"name":"user_id","in":"path","required":true,"schema":{"type":"string","format":"uuid","title":"User Id"}}],"responses":{"200":{"description":"Successful Response","content":{"application/json":{"schema":{}}}},"422":{"description":"Validation Error","content":{"application/json":{"schema":{"$ref":"#/components/schemas/HTTPValidationError"}}}}}}},"/api/admin/users/{user_id}/activate":{"patch":{"tags":["管理者"],"summary":"Activate User","description":"ユーザーをアクティブ化（管理者のみ）","operationId":"activate_user_api_admin_users__user_id__activate_patch","security":[{"HTTPBearer":[]}],"parameters":[{"name":"user_id","in":"path","required":true,"schema":{"type":"string","format":"uuid","title":"User Id"}}],"responses":{"200":{"description":"Successful Response","content":{"application/json":{"schema":{}}}},"422":{"description":"Validation Error","content":{"application/json":{"schema":{"$ref":"#/components/schemas/HTTPValidationError"}}}}}}},"/api/admin/users/{user_id}/deactivate":{"patch":{"tags":["管理者"],"summary":"Deactivate User","description":"ユーザーを非アクティブ化（管理者のみ）","operationId":"deactivate_user_api_admin_users__user_id__deactivate_patch","security":[{"HTTPBearer":[]}],"parameters":[{"name":"user_id","in":"path","required":true,"schema":{"type":"string","format":"uuid","title":"User Id"}}],"responses":{"200":{"description":"Successful Response","content":{"application/json":{"schema":{}}}},"422":{"description":"Validation Error","content":{"application/json":{"schema":{"$ref":"#/components/schemas/HTTPValidationError"}}}}}}}},"components":{"schemas":{"Body_upload_material_api_materials_upload_post":{"properties":{"file":{"type":"string","format":"binary","title":"File"}},"type":"object","required":["file"],"title":"Body_upload_material_api_materials_upload_post"},"HTTPValidationError":{"properties":{"detail":{"items":{"$ref":"#/components/schemas/ValidationError"},"type":"array","title":"Detail"}},"type":"object","title":"HTTPValidationError"},"InvoiceItemResponse":{"properties":{"management_no":{"type":"string","title":"Management No","description":"管理No"},"machine_no":{"type":"string","title":"Machine No","description":"機番"},"actual_hours":{"type":"string","title":"Actual Hours","description":"実工数"},"sort_order":{"type":"integer","title":"Sort Order","description":"並び順","default":0},"id":{"type":"string","format":"uuid","title":"Id"},"invoice_id":{"type":"string","format":"uuid","title":"Invoice Id"},"created_at":{"type":"string","format":"date-time","title":"Created At"}},"type":"object","required":["management_no","machine_no","actual_hours","id","invoice_id","created_at"],"title":"InvoiceItemResponse"},"InvoicePreviewItem":{"properties":{"management_no":{"type":"string","title":"Management No"},"machine_no":{"type":"string","title":"Machine No"},"actual_hours":{"type":"string","title":"Actual Hours"}},"type":"object","required":["management_no","machine_no","actual_hours"],"title":"InvoicePreviewItem"},"InvoicePreviewResponse":{"properties":{"month":{"type":"string","title":"Month"},"total_hours":{"type":"string","title":"Total Hours"},"items":{"items":{"$ref":"#/components/schemas/InvoicePreviewItem"},"type":"array","title":"Items"}},"type":"object","required":["month","total_hours","items"],"title":"InvoicePreviewResponse"},"InvoiceResponse":{"properties":{"invoice_number":{"type":"string","title":"Invoice Number","description":"請求書番号"},"issue_date":{"type":"string","format":"date","title":"Issue Date","description":"発行日"},"status":{"type":"string","title":"Status","description":"ステータス","default":"draft"},"id":{"type":"string","format":"uuid","title":"Id"},"total_amount":{"type":"string","title":"Total Amount"},"created_at":{"type":"string","format":"date-time","title":"Created At"},"updated_at":{"type":"string","format":"date-time","title":"Updated At"},"items":{"items":{"$ref":"#/components/schemas/InvoiceItemResponse"},"type":"array","title":"Items","default":[]}},"type":"object","required":["invoice_number","issue_date","id","total_amount","created_at","updated_at"],"title":"InvoiceResponse"},"InvoiceUpdate":{"properties":{"status":{"anyOf":[{"type":"string"},{"type":"null"}],"title":"Status"}},"type":"object","title":"InvoiceUpdate"},"LoginRequest":{"properties":{"email":{"type":"string","format":"email","title":"Email"},"password":{"type":"string","title":"Password"}},"type":"object","required":["email","password"],"title":"LoginRequest"},"MachineSeriesMasterCreate":{"properties":{"series_name":{"type":"string","maxLength":50,"title":"Series Name","description":"シリーズ名"},"display_name":{"type":"string","maxLength":100,"title":"Display Name","description":"表示名"},"description":{"anyOf":[{"type":"string","maxLength":500},{"type":"null"}],"title":"Description","description":"説明"},"category":{"anyOf":[{"type":"string","maxLength":50},{"type":"null"}],"title":"Category","description":"カテゴリ（標準/特殊）"},"checklist_template_category":{"anyOf":[{"type":"string","maxLength":50},{"type":"null"}],"title":"Checklist Template Category","description":"注意点テンプレート紐付け"},"sort_order":{"type":"integer","title":"Sort Order","description":"並び順","default":0},"is_active":{"type":"boolean","title":"Is Active","description":"有効フラグ","default":true}},"type":"object","required":["series_name","display_name"],"title":"MachineSeriesMasterCreate","description":"機種シリーズマスタ作成用"},"MachineSeriesMasterResponse":{"properties":{"series_name":{"type":"string","maxLength":50,"title":"Series Name","description":"シリーズ名"},"display_name":{"type":"string","maxLength":100,"title":"Display Name","description":"表示名"},"description":{"anyOf":[{"type":"string","maxLength":500},{"type":"null"}],"title":"Description","description":"説明"},"category":{"anyOf":[{"type":"string","maxLength":50},{"type":"null"}],"title":"Category","description":"カテゴリ（標準/特殊）"},"checklist_template_category":{"anyOf":[{"type":"string","maxLength":50},{"type":"null"}],"title":"Checklist Template Category","description":"注意点テンプレート紐付け"},"sort_order":{"type":"integer","title":"Sort Order","description":"並び順","default":0},"is_active":{"type":"boolean","title":"Is Active","description":"有効フラグ","default":true},"id":{"type":"string","format":"uuid","title":"Id"},"created_at":{"type":"string","format":"date-time","title":"Created At"},"updated_at":{"type":"string","format":"date-time","title":"Updated At"}},"type":"object","required":["series_name","display_name","id","created_at","updated_at"],"title":"MachineSeriesMasterResponse","description":"機種シリーズマスタ応答用"},"MachineSeriesMasterUpdate":{"properties":{"series_name":{"anyOf":[{"type":"string","maxLength":50},{"type":"null"}],"title":"Series Name"},"display_name":{"anyOf":[{"type":"string","maxLength":100},{"type":"null"}],"title":"Display Name"},"description":{"anyOf":[{"type":"string","maxLength":500},{"type":"null"}],"title":"Description"},"category":{"anyOf":[{"type":"string","maxLength":50},{"type":"null"}],"title":"Category"},"checklist_template_category":{"anyOf":[{"type":"string","maxLength":50},{"type":"null"}],"title":"Checklist Template Category"},"sort_order":{"anyOf":[{"type":"integer"},{"type":"null"}],"title":"Sort Order"},"is_active":{"anyOf":[{"type":"boolean"},{"type":"null"}],"title":"Is Active"}},"type":"object","title":"MachineSeriesMasterUpdate","description":"機種シリーズマスタ更新用"},"MasterSagyouKubunCreate":{"properties":{"kubun_name":{"type":"string","maxLength":100,"title":"Kubun Name","description":"作業区分名"},"background_color":{"anyOf":[{"type":"string","maxLength":20},{"type":"null"}],"title":"Background Color","description":"背景色（HEXコード）"},"sort_order":{"type":"integer","title":"Sort Order","description":"並び順","default":0},"is_active":{"type":"boolean","title":"Is Active","description":"有効フラグ","default":true}},"type":"object","required":["kubun_name"],"title":"MasterSagyouKubunCreate","description":"作業区分マスタ作成用"},"MasterSagyouKubunResponse":{"properties":{"kubun_name":{"type":"string","maxLength":100,"title":"Kubun Name","description":"作業区分名"},"background_color":{"anyOf":[{"type":"string","maxLength":20},{"type":"null"}],"title":"Background Color","description":"背景色（HEXコード）"},"sort_order":{"type":"integer","title":"Sort Order","description":"並び順","default":0},"is_active":{"type":"boolean","title":"Is Active","description":"有効フラグ","default":true},"id":{"type":"string","format":"uuid","title":"Id"},"created_at":{"type":"string","format":"date-time","title":"Created At"},"updated_at":{"type":"string","format":"date-time","title":"Updated At"}},"type":"object","required":["kubun_name","id","created_at","updated_at"],"title":"MasterSagyouKubunResponse","description":"作業区分マスタ応答用"},"MasterSagyouKubunUpdate":{"properties":{"kubun_name":{"anyOf":[{"type":"string","maxLength":100},{"type":"null"}],"title":"Kubun Name"},"background_color":{"anyOf":[{"type":"string","maxLength":20},{"type":"null"}],"title":"Background Color"},"sort_order":{"anyOf":[{"type":"integer"},{"type":"null"}],"title":"Sort Order"},"is_active":{"anyOf":[{"type":"boolean"},{"type":"null"}],"title":"Is Active"}},"type":"object","title":"MasterSagyouKubunUpdate","description":"作業区分マスタ更新用"},"MasterShinchokuCreate":{"properties":{"status_name":{"type":"string","maxLength":100,"title":"Status Name","description":"進捗ステータス名"},"background_color":{"anyOf":[{"type":"string","maxLength":20},{"type":"null"}],"title":"Background Color","description":"背景色（HEXコード）"},"completion_trigger":{"type":"boolean","title":"Completion Trigger","description":"完了日トリガー","default":false},"start_date_trigger":{"type":"boolean","title":"Start Date Trigger","description":"仕掛日トリガー","default":false},"sort_order":{"type":"integer","title":"Sort Order","description":"並び順","default":0},"is_active":{"type":"boolean","title":"Is Active","description":"有効フラグ","default":true}},"type":"object","required":["status_name"],"title":"MasterShinchokuCreate","description":"進捗マスタ作成用"},"MasterShinchokuResponse":{"properties":{"status_name":{"type":"string","maxLength":100,"title":"Status Name","description":"進捗ステータス名"},"background_color":{"anyOf":[{"type":"string","maxLength":20},{"type":"null"}],"title":"Background Color","description":"背景色（HEXコード）"},"completion_trigger":{"type":"boolean","title":"Completion Trigger","description":"完了日トリガー","default":false},"start_date_trigger":{"type":"boolean","title":"Start Date Trigger","description":"仕掛日トリガー","default":false},"sort_order":{"type":"integer","title":"Sort Order","description":"並び順","default":0},"is_active":{"type":"boolean","title":"Is Active","description":"有効フラグ","default":true},"id":{"type":"string","format":"uuid","title":"Id"},"created_at":{"type":"string","format":"date-time","title":"Created At"},"updated_at":{"type":"string","format":"date-time","title":"Updated At"}},"type":"object","required":["status_name","id","created_at","updated_at"],"title":"MasterShinchokuResponse","description":"進捗マスタ応答用"},"MasterShinchokuUpdate":{"properties":{"status_name":{"anyOf":[{"type":"string","maxLength":100},{"type":"null"}],"title":"Status Name"},"background_color":{"anyOf":[{"type":"string","maxLength":20},{"type":"null"}],"title":"Background Color"},"completion_trigger":{"anyOf":[{"type":"boolean"},{"type":"null"}],"title":"Completion Trigger"},"start_date_trigger":{"anyOf":[{"type":"boolean"},{"type":"null"}],"title":"Start Date Trigger"},"sort_order":{"anyOf":[{"type":"integer"},{"type":"null"}],"title":"Sort Order"},"is_active":{"anyOf":[{"type":"boolean"},{"type":"null"}],"title":"Is Active"}},"type":"object","title":"MasterShinchokuUpdate","description":"進捗マスタ更新用"},"MasterToiawaseCreate":{"properties":{"status_name":{"type":"string","maxLength":100,"title":"Status Name","description":"問い合わせステータス名"},"background_color":{"anyOf":[{"type":"string","maxLength":20},{"type":"null"}],"title":"Background Color","description":"背景色（HEXコード）"},"sort_order":{"type":"integer","title":"Sort Order","description":"並び順","default":0},"is_active":{"type":"boolean","title":"Is Active","description":"有効フラグ","default":true}},"type":"object","required":["status_name"],"title":"MasterToiawaseCreate","description":"問い合わせマスタ作成用"},"MasterToiawaseResponse":{"properties":{"status_name":{"type":"string","maxLength":100,"title":"Status Name","description":"問い合わせステータス名"},"background_color":{"anyOf":[{"type":"string","maxLength":20},{"type":"null"}],"title":"Background Color","description":"背景色（HEXコード）"},"sort_order":{"type":"integer","title":"Sort Order","description":"並び順","default":0},"is_active":{"type":"boolean","title":"Is Active","description":"有効フラグ","default":true},"id":{"type":"string","format":"uuid","title":"Id"},"created_at":{"type":"string","format":"date-time","title":"Created At"},"updated_at":{"type":"string","format":"date-time","title":"Updated At"}},"type":"object","required":["status_name","id","created_at","updated_at"],"title":"MasterToiawaseResponse","description":"問い合わせマスタ応答用"},"MasterToiawaseUpdate":{"properties":{"status_name":{"anyOf":[{"type":"string","maxLength":100},{"type":"null"}],"title":"Status Name"},"background_color":{"anyOf":[{"type":"string","maxLength":20},{"type":"null"}],"title":"Background Color"},"sort_order":{"anyOf":[{"type":"integer"},{"type":"null"}],"title":"Sort Order"},"is_active":{"anyOf":[{"type":"boolean"},{"type":"null"}],"title":"Is Active"}},"type":"object","title":"MasterToiawaseUpdate","description":"問い合わせマスタ更新用"},"MaterialResponse":{"properties":{"title":{"type":"string","title":"Title","description":"資料タイトル"},"machine_no":{"anyOf":[{"type":"string"},{"type":"null"}],"title":"Machine No","description":"特定機番（scope=machineの場合）"},"model":{"anyOf":[{"type":"string"},{"type":"null"}],"title":"Model","description":"特定機種（scope=modelの場合）"},"scope":{"type":"string","title":"Scope","description":"スコープレベル: machine, model, tonnage, series"},"series":{"type":"string","title":"Series","description":"シリーズ名（NEX, HMX等）"},"tonnage":{"anyOf":[{"type":"integer"},{"type":"null"}],"title":"Tonnage","description":"トン数（scope=tonnageの場合）"},"file_path":{"type":"string","title":"File Path","description":"ファイルパス"},"file_size":{"anyOf":[{"type":"integer"},{"type":"null"}],"title":"File Size","description":"ファイルサイズ（バイト）"},"id":{"type":"string","format":"uuid","title":"Id"},"uploaded_by":{"anyOf":[{"type":"string","format":"uuid"},{"type":"null"}],"title":"Uploaded By"},"created_at":{"type":"string","format":"date-time","title":"Created At"}},"type":"object","required":["title","scope","series","file_path","id","uploaded_by","created_at"],"title":"MaterialResponse"},"ProjectCreate":{"properties":{"management_no":{"type":"string","title":"Management No","description":"管理No"},"machine_series_id":{"anyOf":[{"type":"string","format":"uuid"},{"type":"null"}],"title":"Machine Series Id","description":"機種シリーズID"},"generation":{"anyOf":[{"type":"string"},{"type":"null"}],"title":"Generation","description":"世代"},"tonnage":{"anyOf":[{"type":"string"},{"type":"null"}],"title":"Tonnage","description":"トン数"},"spec_tags":{"anyOf":[{"type":"string"},{"type":"null"}],"title":"Spec Tags","description":"仕様タグ"},"machine_no":{"anyOf":[{"type":"string"},{"type":"null"}],"title":"Machine No","description":"機番"},"commission_content":{"anyOf":[{"type":"string"},{"type":"null"}],"title":"Commission Content","description":"業務委託内容"},"toiawase_id":{"anyOf":[{"type":"string","format":"uuid"},{"type":"null"}],"title":"Toiawase Id","description":"問い合わせID"},"sagyou_kubun_id":{"anyOf":[{"type":"string","format":"uuid"},{"type":"null"}],"title":"Sagyou Kubun Id","description":"作業区分ID"},"estimated_hours":{"anyOf":[{"type":"integer"},{"type":"null"}],"title":"Estimated Hours","description":"予定工数（分単位）"},"shinchoku_id":{"anyOf":[{"type":"string","format":"uuid"},{"type":"null"}],"title":"Shinchoku Id","description":"進捗ID"},"start_date":{"anyOf":[{"type":"string","format":"date"},{"type":"null"}],"title":"Start Date","description":"仕掛日"},"completion_date":{"anyOf":[{"type":"string","format":"date"},{"type":"null"}],"title":"Completion Date","description":"完了日"},"drawing_deadline":{"anyOf":[{"type":"string","format":"date"},{"type":"null"}],"title":"Drawing Deadline","description":"作図期限"}},"type":"object","required":["management_no"],"title":"ProjectCreate"},"ProjectListResponse":{"properties":{"projects":{"items":{"$ref":"#/components/schemas/ProjectResponse"},"type":"array","title":"Projects"},"total":{"type":"integer","title":"Total"},"page":{"type":"integer","title":"Page"},"per_page":{"type":"integer","title":"Per Page"}},"type":"object","required":["projects","total","page","per_page"],"title":"ProjectListResponse"},"ProjectResponse":{"properties":{"management_no":{"type":"string","title":"Management No","description":"管理No"},"machine_series_id":{"anyOf":[{"type":"string","format":"uuid"},{"type":"null"}],"title":"Machine Series Id","description":"機種シリーズID"},"generation":{"anyOf":[{"type":"string"},{"type":"null"}],"title":"Generation","description":"世代"},"tonnage":{"anyOf":[{"type":"string"},{"type":"null"}],"title":"Tonnage","description":"トン数"},"spec_tags":{"anyOf":[{"type":"string"},{"type":"null"}],"title":"Spec Tags","description":"仕様タグ"},"machine_no":{"anyOf":[{"type":"string"},{"type":"null"}],"title":"Machine No","description":"機番"},"commission_content":{"anyOf":[{"type":"string"},{"type":"null"}],"title":"Commission Content","description":"業務委託内容"},"toiawase_id":{"anyOf":[{"type":"string","format":"uuid"},{"type":"null"}],"title":"Toiawase Id","description":"問い合わせID"},"sagyou_kubun_id":{"anyOf":[{"type":"string","format":"uuid"},{"type":"null"}],"title":"Sagyou Kubun Id","description":"作業区分ID"},"estimated_hours":{"anyOf":[{"type":"integer"},{"type":"null"}],"title":"Estimated Hours","description":"予定工数（分単位）"},"shinchoku_id":{"anyOf":[{"type":"string","format":"uuid"},{"type":"null"}],"title":"Shinchoku Id","description":"進捗ID"},"start_date":{"anyOf":[{"type":"string","format":"date"},{"type":"null"}],"title":"Start Date","description":"仕掛日"},"completion_date":{"anyOf":[{"type":"string","format":"date"},{"type":"null"}],"title":"Completion Date","description":"完了日"},"drawing_deadline":{"anyOf":[{"type":"string","format":"date"},{"type":"null"}],"title":"Drawing Deadline","description":"作図期限"},"id":{"type":"string","format":"uuid","title":"Id"},"actual_hours":{"type":"integer","title":"Actual Hours","description":"実績工数（分単位）"},"is_active":{"type":"boolean","title":"Is Active"},"created_by":{"anyOf":[{"type":"string","format":"uuid"},{"type":"null"}],"title":"Created By"},"created_at":{"type":"string","format":"date-time","title":"Created At"},"updated_at":{"type":"string","format":"date-time","title":"Updated At"},"machine_series_name":{"anyOf":[{"type":"string"},{"type":"null"}],"title":"Machine Series Name"},"toiawase_name":{"anyOf":[{"type":"string"},{"type":"null"}],"title":"Toiawase Name"},"sagyou_kubun_name":{"anyOf":[{"type":"string"},{"type":"null"}],"title":"Sagyou Kubun Name"},"shinchoku_name":{"anyOf":[{"type":"string"},{"type":"null"}],"title":"Shinchoku Name"}},"type":"object","required":["management_no","id","actual_hours","is_active","created_by","created_at","updated_at"],"title":"ProjectResponse"},"ProjectUpdate":{"properties":{"management_no":{"anyOf":[{"type":"string"},{"type":"null"}],"title":"Management No"},"machine_series_id":{"anyOf":[{"type":"string","format":"uuid"},{"type":"null"}],"title":"Machine Series Id"},"generation":{"anyOf":[{"type":"string"},{"type":"null"}],"title":"Generation"},"tonnage":{"anyOf":[{"type":"string"},{"type":"null"}],"title":"Tonnage"},"spec_tags":{"anyOf":[{"type":"string"},{"type":"null"}],"title":"Spec Tags"},"machine_no":{"anyOf":[{"type":"string"},{"type":"null"}],"title":"Machine No"},"commission_content":{"anyOf":[{"type":"string"},{"type":"null"}],"title":"Commission Content"},"toiawase_id":{"anyOf":[{"type":"string","format":"uuid"},{"type":"null"}],"title":"Toiawase Id"},"sagyou_kubun_id":{"anyOf":[{"type":"string","format":"uuid"},{"type":"null"}],"title":"Sagyou Kubun Id"},"estimated_hours":{"anyOf":[{"type":"integer"},{"type":"null"}],"title":"Estimated Hours"},"shinchoku_id":{"anyOf":[{"type":"string","format":"uuid"},{"type":"null"}],"title":"Shinchoku Id"},"start_date":{"anyOf":[{"type":"string","format":"date"},{"type":"null"}],"title":"Start Date"},"completion_date":{"anyOf":[{"type":"string","format":"date"},{"type":"null"}],"title":"Completion Date"},"drawing_deadline":{"anyOf":[{"type":"string","format":"date"},{"type":"null"}],"title":"Drawing Deadline"},"is_active":{"anyOf":[{"type":"boolean"},{"type":"null"}],"title":"Is Active"}},"type":"object","title":"ProjectUpdate"},"Token":{"properties":{"access_token":{"type":"string","title":"Access Token"},"token_type":{"type":"string","title":"Token Type"}},"type":"object","required":["access_token","token_type"],"title":"Token"},"UserCreate":{"properties":{"email":{"type":"string","format":"email","title":"Email"},"username":{"type":"string","title":"Username"},"password":{"type":"string","title":"Password"}},"type":"object","required":["email","username","password"],"title":"UserCreate"},"UserResponse":{"properties":{"email":{"type":"string","format":"email","title":"Email"},"username":{"type":"string","title":"Username"},"id":{"type":"string","format":"uuid","title":"Id"},"is_active":{"type":"boolean","title":"Is Active"},"is_admin":{"type":"boolean","title":"Is Admin"}},"type":"object","required":["email","username","id","is_active","is_admin"],"title":"UserResponse"},"ValidationError":{"properties":{"loc":{"items":{"anyOf":[{"type":"string"},{"type":"integer"}]},"type":"array","title":"Location"},"msg":{"type":"string","title":"Message"},"type":{"type":"string","title":"Error Type"}},"type":"object","required":["loc","msg","type"],"title":"ValidationError"},"WorkLogCreate":{"properties":{"project_id":{"type":"string","format":"uuid","title":"Project Id","description":"案件ID"},"work_date":{"type":"string","format":"date","title":"Work Date","description":"作業日"},"start_time":{"anyOf":[{"type":"string"},{"type":"null"}],"title":"Start Time","description":"開始時刻（HH:MM形式）"},"end_time":{"anyOf":[{"type":"string"},{"type":"null"}],"title":"End Time","description":"終了時刻（HH:MM形式）"},"duration_minutes":{"type":"integer","exclusiveMinimum":0.0,"title":"Duration Minutes","description":"作業時間（分単位）"},"work_content":{"anyOf":[{"type":"string"},{"type":"null"}],"title":"Work Content","description":"作業内容"}},"type":"object","required":["project_id","work_date","duration_minutes"],"title":"WorkLogCreate"},"WorkLogListResponse":{"properties":{"worklogs":{"items":{"$ref":"#/components/schemas/WorkLogResponse"},"type":"array","title":"Worklogs"},"total":{"type":"integer","title":"Total"},"page":{"type":"integer","title":"Page"},"per_page":{"type":"integer","title":"Per Page"}},"type":"object","required":["worklogs","total","page","per_page"],"title":"WorkLogListResponse"},"WorkLogResponse":{"properties":{"project_id":{"type":"string","format":"uuid","title":"Project Id","description":"案件ID"},"work_date":{"type":"string","format":"date","title":"Work Date","description":"作業日"},"start_time":{"anyOf":[{"type":"string"},{"type":"null"}],"title":"Start Time","description":"開始時刻（HH:MM形式）"},"end_time":{"anyOf":[{"type":"string"},{"type":"null"}],"title":"End Time","description":"終了時刻（HH:MM形式）"},"duration_minutes":{"type":"integer","exclusiveMinimum":0.0,"title":"Duration Minutes","description":"作業時間（分単位）"},"work_content":{"anyOf":[{"type":"string"},{"type":"null"}],"title":"Work Content","description":"作業内容"},"id":{"type":"string","format":"uuid","title":"Id"},"user_id":{"type":"string","format":"uuid","title":"User Id"},"created_at":{"type":"string","format":"date-time","title":"Created At"},"updated_at":{"type":"string","format":"date-time","title":"Updated At"}},"type":"object","required":["project_id","work_date","duration_minutes","id","user_id","created_at","updated_at"],"title":"WorkLogResponse"},"WorkLogUpdate":{"properties":{"project_id":{"anyOf":[{"type":"string","format":"uuid"},{"type":"null"}],"title":"Project Id"},"work_date":{"anyOf":[{"type":"string","format":"date"},{"type":"null"}],"title":"Work Date"},"start_time":{"anyOf":[{"type":"string"},{"type":"null"}],"title":"Start Time"},"end_time":{"anyOf":[{"type":"string"},{"type":"null"}],"title":"End Time"},"duration_minutes":{"anyOf":[{"type":"integer","exclusiveMinimum":0.0},{"type":"null"}],"title":"Duration Minutes"},"work_content":{"anyOf":[{"type":"string"},{"type":"null"}],"title":"Work Content"}},"type":"object","title":"WorkLogUpdate"}},"securitySchemes":{"HTTPBearer":{"type":"http","scheme":"bearer"}}}}